discordrouter/__init__.py
discordrouter/router.py
discordrouter-0.0.5.dist-info/METADATA
discordrouter-0.0.5.dist-info/WHEEL
discordrouter-0.0.5.dist-info/top_level.txt
discordrouter-0.0.5.dist-info/RECORD
