Metadata-Version: 2.1
Name: discordrouter
Version: 0.0.5
Summary: Decorator for discord.py chat bots
Home-page: https://github.com/t94j0/discord-router
Author: Max Harley
Author-email: maxh@maxh.io
License: UNKNOWN
Platform: UNKNOWN
Classifier: Programming Language :: Python :: 3
Classifier: Operating System :: OS Independent
